emberfactory/__init__.py
emberfactory/control.py
emberfactory/helpers.py
emberfactory/makember.py
emberfactory/sitenav.py
emberfactory/doc/examples.md
emberfactory/doc/parameters.md
emberfactory/doc/tutorial.md
emberfactory/doc/examples/AR5-SR15-RFCs.xlsx
emberfactory/doc/examples/AR5-SYR-CO2.xlsx
emberfactory/doc/examples/Basic-layout-SRCCL.xlsx
emberfactory/doc/examples/Benefits_and_risks.xlsx
emberfactory/doc/examples/Ember_metadata.xlsx
emberfactory/doc/examples/RFCs-data-2020_01_26-Z2020_rev1_byPubli.xlsx
emberfactory/doc/examples/SROCC_SPM3.xlsx
emberfactory/doc/examples/Standard-fmt-SRCCL.xlsx
emberfactory/doc/examples/colors.xlsx
emberfactory/doc/examples/template.xlsx
emberfactory/doc/examples/images/AR5-SR15-RFCs.png
emberfactory/doc/examples/images/AR5-SYR-CO2.png
emberfactory/doc/examples/images/Benefits_and_risks.png
emberfactory/doc/examples/images/SROCC_SPM3.png
emberfactory/static/apple-touch-icon-180.png
emberfactory/static/ef-gp-definitions.png
emberfactory/static/emberapps.css
emberfactory/static/emberfactory.png
emberfactory/static/favicon.ico
emberfactory/static/icons.svg
emberfactory/templates/base.html
emberfactory/templates/emberfactory/doc.html
emberfactory/templates/emberfactory/error.html
emberfactory/templates/emberfactory/more.html
emberfactory/templates/emberfactory/result.html
emberfactory/templates/emberfactory/start.html
EmberFactory-2.1.0.dist-info/LICENCE.md
EmberFactory-2.1.0.dist-info/METADATA
EmberFactory-2.1.0.dist-info/WHEEL
EmberFactory-2.1.0.dist-info/top_level.txt
EmberFactory-2.1.0.dist-info/RECORD
