Metadata-Version: 2.1
Name: EmberFactory
Version: 2.1.0
Summary: Software to (re)produce burning ember diagrams of the style used in IPCC reports.
Home-page: https://framagit.org/marbaix/ember-factory
Author: Philippe Marbaix
Author-email: philippe.marbaix@uclouvain.be
Maintainer: Philippe Marbaix
Maintainer-email: philippe.marbaix@uclouvain.be
License: GNU General Public License 3 or later
Project-URL: Source, https://framagit.org/marbaix/ember-factory
Project-URL: Website, https://climrisk.org/emberfactory/
Classifier: Framework :: Flask
Classifier: Programming Language :: Python :: 3
Requires-Python: >=3.10
License-File: LICENCE.md
Requires-Dist: Flask
Requires-Dist: Werkzeug
Requires-Dist: Markdown
Requires-Dist: setuptools
Requires-Dist: numpy
Requires-Dist: reportlab
Requires-Dist: svg-py
Requires-Dist: defusedxml
Requires-Dist: openpyxl
Requires-Dist: pdf2image
Requires-Dist: APScheduler
Requires-Dist: pytest
Requires-Dist: embermaker
